plutto/__init__.py
plutto/client.py
plutto/constants.py
plutto/core.py
plutto/errors.py
plutto/managers/__init__.py
plutto/managers/customers_manager.py
plutto/managers/invoices_manager.py
plutto/managers/meter_events_manager.py
plutto/managers/permission_groups_manager.py
plutto/managers/products_manager.py
plutto/managers/subscriptions_manager.py
plutto/mixins/__init__.py
plutto/mixins/manager_mixin.py
plutto/mixins/resource_mixin.py
plutto/paginator.py
plutto/resource_handlers.py
plutto/resources/__init__.py
plutto/resources/customer.py
plutto/resources/customer_permission.py
plutto/resources/generic_plutto_resource.py
plutto/resources/invoice.py
plutto/resources/meter_event.py
plutto/resources/permission_group.py
plutto/resources/product.py
plutto/resources/subscription.py
plutto/utils.py
plutto/version.py
plutto-0.2.0.dist-info/WHEEL
plutto-0.2.0.dist-info/METADATA
plutto-0.2.0.dist-info/RECORD
