Metadata-Version: 2.1
Name: plutto
Version: 0.2.0
Summary: The official Python client for Plutto API
Home-page: https://getplutto.com/
License: BSD-3-Clause
Author: Nicolas Massardo
Author-email: nmassardot@uc.cl
Requires-Python: >=3.7,<4.0
Classifier: License :: OSI Approved :: BSD License
Classifier: Programming Language :: Python :: 3
Classifier: Programming Language :: Python :: 3.10
Classifier: Programming Language :: Python :: 3.7
Classifier: Programming Language :: Python :: 3.8
Classifier: Programming Language :: Python :: 3.9
Requires-Dist: httpx (>=0.16,<1.0)
Project-URL: Repository, https://github.com/plutto-labs/plutto-python
